helloworld.py
helloworld_hendi-0.0.1.dist-info/METADATA
helloworld_hendi-0.0.1.dist-info/WHEEL
helloworld_hendi-0.0.1.dist-info/top_level.txt
helloworld_hendi-0.0.1.dist-info/RECORD
