Metadata-Version: 2.1
Name: helloworld-hendi
Version: 0.0.1
Summary: Say hello!
License: UNKNOWN
Platform: UNKNOWN
